MANIFEST.in
README.md
setup.py
ann_solo/SpectrumMatch.cpp
ann_solo/SpectrumMatch.h
ann_solo/__init__.py
ann_solo/ann_solo.py
ann_solo/config.py
ann_solo/parsers.cpp
ann_solo/parsers.pyx
ann_solo/plot_ssm.py
ann_solo/reader.py
ann_solo/spectral_library.py
ann_solo/spectrum.py
ann_solo/spectrum_match.cpp
ann_solo/spectrum_match.pyx
ann_solo/utils.py
ann_solo/writer.py
ann_solo.egg-info/PKG-INFO
ann_solo.egg-info/SOURCES.txt
ann_solo.egg-info/dependency_links.txt
ann_solo.egg-info/entry_points.txt
ann_solo.egg-info/requires.txt
ann_solo.egg-info/top_level.txt
ann_solo/ms_io/parsers.cpp